sched2/__init__.py
sched2-0.8.3.dist-info/METADATA
sched2-0.8.3.dist-info/WHEEL
sched2-0.8.3.dist-info/licenses/LICENSE
sched2-0.8.3.dist-info/RECORD
