Metadata-Version: 2.4
Name: sched2
Version: 0.8.3
Summary: Event scheduler 2
Project-URL: homepage, https://medecau.github.io/sched2/
Author-email: Pedro Rodrigues <me@pdbr.org>
License: MIT License
License-File: LICENSE
Requires-Python: <4.0,>=3.8
